reasoning_kernel/__init__.py
reasoning_kernel/__version__.py
reasoning_kernel/config.py
reasoning_kernel/kernel.py
reasoning_kernel/main.py
reasoning_kernel/settings.py
reasoning_kernel/settings_minimal.py
reasoning_kernel/plugins/__init__.py
reasoning_kernel/plugins/base_plugin.py
reasoning_kernel/plugins/knowledge.py
reasoning_kernel/plugins/knowledge_plugin.py
reasoning_kernel/plugins/knowledge_plugin_sk.py
reasoning_kernel/plugins/msa_reasoning.py
reasoning_kernel/plugins/msa_reasoning_enhanced.py
reasoning_kernel/plugins/msa_reasoning_simple.py
reasoning_kernel/plugins/parse_plugin.py
reasoning_kernel/plugins/plugin_registry.py
reasoning_kernel/plugins/synthesis_plugin.py
reasoning_kernel/plugins/world_model.py
reasoning_kernel/services/__init__.py
reasoning_kernel/services/daytona.py
reasoning_kernel/services/daytona_numpyro_executor.py
reasoning_kernel/services/daytona_ppl_executor.py
reasoning_kernel/services/daytona_sandbox_manager.py
reasoning_kernel/services/daytona_service.py
reasoning_kernel/services/hierarchical_world_model_manager.py
reasoning_kernel/services/langcache_service.py
reasoning_kernel/services/memory_service.py
reasoning_kernel/services/msa_redis_integration.py
reasoning_kernel/services/redis.py
reasoning_kernel/services/redis_connection.py
reasoning_kernel/services/redis_knowledge.py
reasoning_kernel/services/redis_maintenance.py
reasoning_kernel/services/redis_service.py
reasoning_kernel/services/redis_session_cache.py
reasoning_kernel/services/redis_vectors.py
reasoning_kernel/services/redis_world_model.py
reasoning_kernel/services/unified_redis_service.py
reasoning_kernel/services/web_search_service.py
reasoning_kernel/sk_core/api_integration.py
reasoning_kernel/sk_core/cli_commands.py
reasoning_kernel-2.0.0.dist-info/METADATA
reasoning_kernel-2.0.0.dist-info/WHEEL
reasoning_kernel-2.0.0.dist-info/entry_points.txt
reasoning_kernel-2.0.0.dist-info/RECORD
