Metadata-Version: 2.4
Name: reasoning-kernel
Version: 2.0.0
Summary: SK-native MSA Architecture for Advanced Reasoning
Project-URL: Documentation, https://github.com/qredence/reasoning-kernel#readme
Project-URL: Issues, https://github.com/qredence/reasoning-kernel/issues
Project-URL: Source, https://github.com/qredence/reasoning-kernel
Author-email: Qredence Team <contact@qredence.ai>
License: MIT
Keywords: ai,msa,probabilistic-programming,reasoning,semantic-kernel
Classifier: Development Status :: 4 - Beta
Classifier: Intended Audience :: Developers
Classifier: License :: OSI Approved :: MIT License
Classifier: Operating System :: OS Independent
Classifier: Programming Language :: Python :: 3
Classifier: Programming Language :: Python :: 3.10
Classifier: Programming Language :: Python :: 3.11
Classifier: Programming Language :: Python :: 3.12
Classifier: Programming Language :: Python :: 3.13
Classifier: Topic :: Scientific/Engineering :: Artificial Intelligence
Classifier: Topic :: Software Development :: Libraries :: Python Modules
Requires-Python: <3.14,>=3.10
Requires-Dist: aiohttp>=3.9.0
Requires-Dist: aioredis<3.0.0,>=2.0.0
Requires-Dist: click>=8.1.0
Requires-Dist: fastapi<1.0.0,>=0.104.0
Requires-Dist: httpx>=0.27.0
Requires-Dist: numpy>=1.24.0
Requires-Dist: numpyro>=0.15.0
Requires-Dist: pandas>=2.0.0
Requires-Dist: pydantic-settings<3.0.0,>=2.0.0
Requires-Dist: pydantic<3.0.0,>=2.0.0
Requires-Dist: pyro-ppl>=1.8.0
Requires-Dist: python-dotenv>=1.0.0
Requires-Dist: redis<6.0.0,>=5.0.0
Requires-Dist: rich>=13.0.0
Requires-Dist: scipy>=1.11.0
Requires-Dist: semantic-kernel<2.0.0,>=1.36.0
Requires-Dist: tensorflow-probability>=0.24.0
Requires-Dist: typing-extensions>=4.8.0
Requires-Dist: uvicorn[standard]<1.0.0,>=0.24.0
Provides-Extra: all
Requires-Dist: mkdocs-material>=9.5.0; extra == 'all'
Requires-Dist: mkdocs>=1.5.0; extra == 'all'
Requires-Dist: mkdocstrings[python]>=0.24.0; extra == 'all'
Requires-Dist: mypy>=1.8.0; extra == 'all'
Requires-Dist: pre-commit>=3.6.0; extra == 'all'
Requires-Dist: pytest-asyncio>=0.23.0; extra == 'all'
Requires-Dist: pytest-benchmark>=4.0.0; extra == 'all'
Requires-Dist: pytest-cov>=4.0.0; extra == 'all'
Requires-Dist: pytest-mock>=3.12.0; extra == 'all'
Requires-Dist: pytest>=8.0.0; extra == 'all'
Requires-Dist: ruff>=0.1.0; extra == 'all'
Provides-Extra: dev
Requires-Dist: mypy>=1.8.0; extra == 'dev'
Requires-Dist: pre-commit>=3.6.0; extra == 'dev'
Requires-Dist: pytest-asyncio>=0.23.0; extra == 'dev'
Requires-Dist: pytest-cov>=4.0.0; extra == 'dev'
Requires-Dist: pytest>=8.0.0; extra == 'dev'
Requires-Dist: ruff>=0.1.0; extra == 'dev'
Provides-Extra: docs
Requires-Dist: mkdocs-material>=9.5.0; extra == 'docs'
Requires-Dist: mkdocs>=1.5.0; extra == 'docs'
Requires-Dist: mkdocstrings[python]>=0.24.0; extra == 'docs'
Provides-Extra: test
Requires-Dist: pytest-asyncio>=0.23.0; extra == 'test'
Requires-Dist: pytest-benchmark>=4.0.0; extra == 'test'
Requires-Dist: pytest-mock>=3.12.0; extra == 'test'
Requires-Dist: pytest>=8.0.0; extra == 'test'
